hatch_cpp/__init__.py
hatch_cpp/config.py
hatch_cpp/hooks.py
hatch_cpp/plugin.py
hatch_cpp/utils.py
hatch_cpp/tests/test_hatch_build.py
hatch_cpp/tests/test_projects.py
hatch_cpp/tests/test_structs.py
hatch_cpp/tests/test_project_basic/pyproject.toml
hatch_cpp/tests/test_project_basic/cpp/project/basic.cpp
hatch_cpp/tests/test_project_basic/cpp/project/basic.hpp
hatch_cpp/tests/test_project_basic/project/__init__.py
hatch_cpp/tests/test_project_cmake/CMakeLists.txt
hatch_cpp/tests/test_project_cmake/Makefile
hatch_cpp/tests/test_project_cmake/pyproject.toml
hatch_cpp/tests/test_project_cmake/cpp/project/basic.cpp
hatch_cpp/tests/test_project_cmake/cpp/project/basic.hpp
hatch_cpp/tests/test_project_cmake/project/__init__.py
hatch_cpp/tests/test_project_cmake/project/include/project/basic.hpp
hatch_cpp/tests/test_project_cmake_vcpkg/CMakeLists.txt
hatch_cpp/tests/test_project_cmake_vcpkg/Makefile
hatch_cpp/tests/test_project_cmake_vcpkg/pyproject.toml
hatch_cpp/tests/test_project_cmake_vcpkg/vcpkg.json
hatch_cpp/tests/test_project_cmake_vcpkg/cpp/project/basic.cpp
hatch_cpp/tests/test_project_cmake_vcpkg/cpp/project/basic.hpp
hatch_cpp/tests/test_project_cmake_vcpkg/project/__init__.py
hatch_cpp/tests/test_project_cmake_vcpkg/project/include/project/basic.hpp
hatch_cpp/tests/test_project_hatch_build/pyproject.toml
hatch_cpp/tests/test_project_hatch_build/cpp/project/basic.cpp
hatch_cpp/tests/test_project_hatch_build/cpp/project/basic.hpp
hatch_cpp/tests/test_project_hatch_build/project/__init__.py
hatch_cpp/tests/test_project_limited_api/pyproject.toml
hatch_cpp/tests/test_project_limited_api/cpp/project/basic.cpp
hatch_cpp/tests/test_project_limited_api/cpp/project/basic.hpp
hatch_cpp/tests/test_project_limited_api/project/__init__.py
hatch_cpp/tests/test_project_nanobind/pyproject.toml
hatch_cpp/tests/test_project_nanobind/cpp/project/basic.cpp
hatch_cpp/tests/test_project_nanobind/cpp/project/basic.hpp
hatch_cpp/tests/test_project_nanobind/project/__init__.py
hatch_cpp-0.2.2.dist-info/METADATA
hatch_cpp-0.2.2.dist-info/WHEEL
hatch_cpp-0.2.2.dist-info/entry_points.txt
hatch_cpp-0.2.2.dist-info/licenses/LICENSE
hatch_cpp-0.2.2.dist-info/RECORD
